README.md
setup.py
dbot_metrics/__init__.py
dbot_metrics/base_metric.py
dbot_metrics/configuation.py
dbot_metrics/dbotmetrics_collector.py
dbot_metrics/metric_exception.py
dbot_metrics/timer.py
dbot_metrics/version.py
dbot_metrics.egg-info/PKG-INFO
dbot_metrics.egg-info/SOURCES.txt
dbot_metrics.egg-info/dependency_links.txt
dbot_metrics.egg-info/requires.txt
dbot_metrics.egg-info/top_level.txt
dbot_metrics/output/__init__.py
dbot_metrics/output/leveldb_client.py
dbot_metrics/output/output_plugin.py