Metadata-Version: 2.1
Name: dbot-metrics
Version: 0.1.5
Summary: ATN atn dbot metrics package
Home-page: https://github.com/ATNIO/metrics
Author: xiaoch05
Author-email: xiaoch2010@gmail.com
License: UNKNOWN
Platform: UNKNOWN
Classifier: Programming Language :: Python :: 3
Classifier: License :: OSI Approved :: MIT License
Classifier: Operating System :: OS Independent
